[
    {
        "x": 87,
        "y": 12,
        "label_id": 1
    },
    {
        "x": 133,
        "y": 14,
        "label_id": 1
    },
    {
        "x": 484,
        "y": 33,
        "label_id": 1
    },
    {
        "x": 39,
        "y": 39,
        "label_id": 1
    },
    {
        "x": 147,
        "y": 45,
        "label_id": 1
    },
    {
        "x": 539,
        "y": 48,
        "label_id": 1
    },
    {
        "x": 587,
        "y": 54,
        "label_id": 1
    },
    {
        "x": 620,
        "y": 55,
        "label_id": 1
    },
    {
        "x": 272,
        "y": 59,
        "label_id": 1
    },
    {
        "x": 22,
        "y": 76,
        "label_id": 1
    },
    {
        "x": 536,
        "y": 90,
        "label_id": 1
    },
    {
        "x": 464,
        "y": 126,
        "label_id": 1
    },
    {
        "x": 202,
        "y": 142,
        "label_id": 1
    },
    {
        "x": 589,
        "y": 152,
        "label_id": 1
    },
    {
        "x": 558,
        "y": 169,
        "label_id": 1
    },
    {
        "x": 235,
        "y": 171,
        "label_id": 1
    },
    {
        "x": 522,
        "y": 174,
        "label_id": 1
    },
    {
        "x": 469,
        "y": 183,
        "label_id": 1
    },
    {
        "x": 215,
        "y": 194,
        "label_id": 1
    },
    {
        "x": 504,
        "y": 212,
        "label_id": 1
    },
    {
        "x": 370,
        "y": 227,
        "label_id": 1
    },
    {
        "x": 413,
        "y": 229,
        "label_id": 1
    },
    {
        "x": 527,
        "y": 259,
        "label_id": 1
    },
    {
        "x": 206,
        "y": 262,
        "label_id": 1
    },
    {
        "x": 376,
        "y": 272,
        "label_id": 1
    },
    {
        "x": 95,
        "y": 273,
        "label_id": 1
    },
    {
        "x": 565,
        "y": 283,
        "label_id": 1
    },
    {
        "x": 422,
        "y": 286,
        "label_id": 1
    },
    {
        "x": 538,
        "y": 293,
        "label_id": 1
    },
    {
        "x": 174,
        "y": 299,
        "label_id": 1
    },
    {
        "x": 502,
        "y": 304,
        "label_id": 1
    },
    {
        "x": 79,
        "y": 313,
        "label_id": 1
    },
    {
        "x": 448,
        "y": 324,
        "label_id": 1
    },
    {
        "x": 370,
        "y": 327,
        "label_id": 1
    },
    {
        "x": 163,
        "y": 337,
        "label_id": 1
    },
    {
        "x": 549,
        "y": 346,
        "label_id": 1
    },
    {
        "x": 63,
        "y": 356,
        "label_id": 1
    },
    {
        "x": 343,
        "y": 377,
        "label_id": 1
    },
    {
        "x": 389,
        "y": 380,
        "label_id": 1
    },
    {
        "x": 6,
        "y": 398,
        "label_id": 1
    },
    {
        "x": 121,
        "y": 403,
        "label_id": 1
    },
    {
        "x": 69,
        "y": 410,
        "label_id": 1
    },
    {
        "x": 145,
        "y": 411,
        "label_id": 1
    },
    {
        "x": 389,
        "y": 424,
        "label_id": 1
    },
    {
        "x": 418,
        "y": 424,
        "label_id": 1
    },
    {
        "x": 457,
        "y": 442,
        "label_id": 1
    },
    {
        "x": 125,
        "y": 461,
        "label_id": 1
    },
    {
        "x": 478,
        "y": 486,
        "label_id": 1
    },
    {
        "x": 138,
        "y": 489,
        "label_id": 1
    },
    {
        "x": 431,
        "y": 515,
        "label_id": 1
    },
    {
        "x": 50,
        "y": 525,
        "label_id": 1
    },
    {
        "x": 574,
        "y": 535,
        "label_id": 1
    },
    {
        "x": 425,
        "y": 548,
        "label_id": 1
    },
    {
        "x": 384,
        "y": 591,
        "label_id": 1
    },
    {
        "x": 545,
        "y": 628,
        "label_id": 1
    },
    {
        "x": 192,
        "y": 631,
        "label_id": 1
    },
    {
        "x": 634,
        "y": 130,
        "label_id": 1
    },
    {
        "x": 448,
        "y": 4,
        "label_id": 1
    },
    {
        "x": 353,
        "y": 25,
        "label_id": 2
    },
    {
        "x": 593,
        "y": 25,
        "label_id": 2
    },
    {
        "x": 106,
        "y": 47,
        "label_id": 2
    },
    {
        "x": 68,
        "y": 50,
        "label_id": 2
    },
    {
        "x": 344,
        "y": 60,
        "label_id": 2
    },
    {
        "x": 406,
        "y": 65,
        "label_id": 2
    },
    {
        "x": 83,
        "y": 77,
        "label_id": 2
    },
    {
        "x": 294,
        "y": 78,
        "label_id": 2
    },
    {
        "x": 442,
        "y": 87,
        "label_id": 2
    },
    {
        "x": 371,
        "y": 88,
        "label_id": 2
    },
    {
        "x": 408,
        "y": 103,
        "label_id": 2
    },
    {
        "x": 430,
        "y": 103,
        "label_id": 2
    },
    {
        "x": 342,
        "y": 105,
        "label_id": 2
    },
    {
        "x": 163,
        "y": 127,
        "label_id": 2
    },
    {
        "x": 27,
        "y": 131,
        "label_id": 2
    },
    {
        "x": 326,
        "y": 133,
        "label_id": 2
    },
    {
        "x": 410,
        "y": 133,
        "label_id": 2
    },
    {
        "x": 383,
        "y": 147,
        "label_id": 2
    },
    {
        "x": 15,
        "y": 150,
        "label_id": 2
    },
    {
        "x": 345,
        "y": 152,
        "label_id": 2
    },
    {
        "x": 173,
        "y": 163,
        "label_id": 2
    },
    {
        "x": 71,
        "y": 164,
        "label_id": 2
    },
    {
        "x": 296,
        "y": 172,
        "label_id": 2
    },
    {
        "x": 288,
        "y": 203,
        "label_id": 2
    },
    {
        "x": 319,
        "y": 204,
        "label_id": 2
    },
    {
        "x": 182,
        "y": 211,
        "label_id": 2
    },
    {
        "x": 103,
        "y": 234,
        "label_id": 2
    },
    {
        "x": 248,
        "y": 237,
        "label_id": 2
    },
    {
        "x": 263,
        "y": 253,
        "label_id": 2
    },
    {
        "x": 567,
        "y": 253,
        "label_id": 2
    },
    {
        "x": 131,
        "y": 258,
        "label_id": 2
    },
    {
        "x": 296,
        "y": 259,
        "label_id": 2
    },
    {
        "x": 628,
        "y": 266,
        "label_id": 2
    },
    {
        "x": 218,
        "y": 327,
        "label_id": 2
    },
    {
        "x": 254,
        "y": 332,
        "label_id": 2
    },
    {
        "x": 235,
        "y": 338,
        "label_id": 2
    },
    {
        "x": 239,
        "y": 369,
        "label_id": 2
    },
    {
        "x": 467,
        "y": 372,
        "label_id": 2
    },
    {
        "x": 625,
        "y": 423,
        "label_id": 2
    },
    {
        "x": 24,
        "y": 445,
        "label_id": 2
    },
    {
        "x": 534,
        "y": 450,
        "label_id": 2
    },
    {
        "x": 563,
        "y": 460,
        "label_id": 2
    },
    {
        "x": 207,
        "y": 473,
        "label_id": 2
    },
    {
        "x": 598,
        "y": 488,
        "label_id": 2
    },
    {
        "x": 66,
        "y": 488,
        "label_id": 2
    },
    {
        "x": 251,
        "y": 499,
        "label_id": 2
    },
    {
        "x": 350,
        "y": 506,
        "label_id": 2
    },
    {
        "x": 520,
        "y": 516,
        "label_id": 2
    },
    {
        "x": 236,
        "y": 522,
        "label_id": 2
    },
    {
        "x": 374,
        "y": 528,
        "label_id": 2
    },
    {
        "x": 311,
        "y": 530,
        "label_id": 2
    },
    {
        "x": 176,
        "y": 532,
        "label_id": 2
    },
    {
        "x": 629,
        "y": 544,
        "label_id": 2
    },
    {
        "x": 278,
        "y": 544,
        "label_id": 2
    },
    {
        "x": 196,
        "y": 549,
        "label_id": 2
    },
    {
        "x": 476,
        "y": 551,
        "label_id": 2
    },
    {
        "x": 294,
        "y": 564,
        "label_id": 2
    },
    {
        "x": 497,
        "y": 573,
        "label_id": 2
    },
    {
        "x": 435,
        "y": 586,
        "label_id": 2
    },
    {
        "x": 566,
        "y": 596,
        "label_id": 2
    },
    {
        "x": 604,
        "y": 601,
        "label_id": 2
    },
    {
        "x": 288,
        "y": 613,
        "label_id": 2
    },
    {
        "x": 455,
        "y": 619,
        "label_id": 2
    },
    {
        "x": 98,
        "y": 623,
        "label_id": 2
    },
    {
        "x": 506,
        "y": 626,
        "label_id": 2
    },
    {
        "x": 596,
        "y": 630,
        "label_id": 2
    },
    {
        "x": 409,
        "y": 635,
        "label_id": 2
    }
]